Metadata-Version: 2.1
Name: estrela
Version: 2025.1.0.0
Summary: Uma biblioteca de exemplo simples para ensino
Home-page: https://github.com/xxxxx/dobro
Author: maria eduarda
Author-email: mariaeduarda.e.m32360824@gmai.com
Classifier: Programming Language :: Python :: 3
Classifier: License :: OSI Approved :: MIT License
Classifier: Natural Language :: Portuguese (Brazilian)
Requires-Python: >=3.6
License-File: LICENSE.txt
